swai/__init__.py
swai/cli.py
swai/const.py
swai/controller.py
swai/tasks.py
swai/user.py
swai/version.py
swai/data_precess/__init__.py
swai/data_precess/base_preprocess.py
swai/data_precess/swbind.py
swai/data_precess/swdocking.py
swai/utils/__init__.py
swai/utils/log.py
swai/utils/print_once.py
swai/utils/test_dependence.py
swai-0.1.1.dist-info/METADATA
swai-0.1.1.dist-info/WHEEL
swai-0.1.1.dist-info/entry_points.txt
swai-0.1.1.dist-info/top_level.txt
swai-0.1.1.dist-info/RECORD
