Metadata-Version: 2.4
Name: swai
Version: 0.1.1
Summary: thuway ai tools
Home-page: https://www.thuwaytec.com/
License: Apache License 2.0
Requires-Python: >=3.8
Requires-Dist: requests
Requires-Dist: tabulate
Requires-Dist: numpy>=1.24.0
Dynamic: description
Dynamic: description-content-type
Dynamic: home-page
Dynamic: license
Dynamic: requires-dist
Dynamic: requires-python
Dynamic: summary
